airflow_unicore_integration/__init__.py
airflow_unicore_integration/executors/__init__.py
airflow_unicore_integration/executors/run_task_via_supervisor.py
airflow_unicore_integration/executors/unicore_executor.py
airflow_unicore_integration/hooks/__init__.py
airflow_unicore_integration/hooks/unicore_hooks.py
airflow_unicore_integration/operators/__init__.py
airflow_unicore_integration/operators/unicore_operators.py
airflow_unicore_integration/policies/__init__.py
airflow_unicore_integration/util/job.py
airflow_unicore_integration/util/launch_script_content.py
airflow_unicore_integration-0.1.12.dist-info/licenses/LICENSE
airflow_unicore_integration-0.1.12.dist-info/METADATA
airflow_unicore_integration-0.1.12.dist-info/WHEEL
airflow_unicore_integration-0.1.12.dist-info/entry_points.txt
airflow_unicore_integration-0.1.12.dist-info/top_level.txt
airflow_unicore_integration-0.1.12.dist-info/RECORD
