Metadata-Version: 2.4
Name: airflow-unicore-integration
Version: 0.1.12
Summary: Running Unicore Jobs from airflow DAGs.
Author-email: Christian Böttcher <c.boettcher@fz-juelich.de>
License-Expression: BSD-3-Clause
Project-URL: Homepage, https://github.com/UNICORE-EU/airflow-unicore-integration
Project-URL: Issues, https://github.com/UNICORE-EU/airflow-unicore-integration/issues
Classifier: Development Status :: 4 - Beta
Classifier: Framework :: Apache Airflow :: Provider
Classifier: Programming Language :: Python :: 3
Classifier: Operating System :: OS Independent
Requires-Python: >=3.9
License-File: LICENSE
Requires-Dist: pyunicore>=1.0.0
Requires-Dist: apache-airflow>=3.0.0
Dynamic: license-file
